AUTHORS
LICENSE
MANIFEST.in
setup.py
django_geoip_redirection/__init__.py
django_geoip_redirection/middleware.py
django_geoip_redirection/models.py
django_geoip_redirection/tests.py
django_geoip_redirection/views.py
django_geoip_redirection.egg-info/PKG-INFO
django_geoip_redirection.egg-info/SOURCES.txt
django_geoip_redirection.egg-info/dependency_links.txt
django_geoip_redirection.egg-info/not-zip-safe
django_geoip_redirection.egg-info/top_level.txt
django_geoip_redirection/tests/__init__.py
django_geoip_redirection/tests/models.py
django_geoip_redirection/tests/tests.py
django_geoip_redirection/tests/urls.py